<?xml version="1.0" encoding="UTF-8"?>
<model name="lcsTranslation" xmlns:xsi="http://www.w3.org/2001/XMLSchema-instance"
	xmlns="http://schema.qcadoo.org/model"
	xsi:schemaLocation="http://schema.qcadoo.org/model http://schema.qcadoo.org/model.xsd">
	<fields>
		<belongsTo name="translation" model="translation" lazy="false" required="true" />
		<belongsTo name="lcs" model="lcs" lazy="true" required="true" />
	</fields>
	<hooks>
		<validatesWith class="com.qcadoo.mes.lcs.LcsModelService" method="validatorTranslationUniqe" />
	</hooks>
	<identifier expression="#translation.name" />
</model>